taminus/__init__.py
taminus/main.py
taminus/utils.py
taminus-0.0.8.dist-info/LICENSE
taminus-0.0.8.dist-info/METADATA
taminus-0.0.8.dist-info/WHEEL
taminus-0.0.8.dist-info/top_level.txt
taminus-0.0.8.dist-info/RECORD
